{
  "transactionId": "124521",
  "recordType": "Form",
  "RecordId": "21",
  "author": "garrett.kim@gmail.com",
  "transactionType": "update",
  "changedFields": ["name", "questionGroups", "questionGroups[0].title"],
  "newRecord": {
    "name": "newName",
    "questionGroups": [
      {
        "title": "updated title"
      },
      {
        "title": "unchanged title"
      }
    ]
  },
  "oldRecord": {
    "name": "oldName",
    "questionGroups": [
      {
        "title": "old title"
      },
      {
        "title": "unchanged title"
      }
    ]
  }
}